vrsbindings.cpython-310-x86_64-linux-gnu.so
vrs-1.2.1.dist-info/WHEEL
vrs-1.2.1.dist-info/LICENSE
vrs-1.2.1.dist-info/top_level.txt
vrs-1.2.1.dist-info/RECORD
vrs-1.2.1.dist-info/METADATA
vrs.libs/libzstd-8d126cbb.so.1.5.5
vrs.libs/libboost_date_time-32b0e713.so.1.81.0
vrs.libs/libboost_thread-c7007958.so.1.81.0
vrs.libs/libjpeg-7b6a55ae.so.8.2.2
vrs.libs/libpng15-ce838cd1.so.15.13.0
vrs.libs/libboost_atomic-489c2d94.so.1.81.0
vrs.libs/libboost_system-4a7650ea.so.1.81.0
vrs.libs/libboost_chrono-fee1b1d2.so.1.81.0
vrs.libs/libboost_filesystem-e610b554.so.1.81.0
vrs.libs/libxxhash-5b835a6a.so.0.8.2
vrs.libs/liblz4-af1653fb.so.1.8.3
vrs.libs/libturbojpeg-6b1ec943.so.0.2.0
pyvrs/__init__.py
pyvrs/slice.py
pyvrs/record.py
pyvrs/base.py
pyvrs/utils.py
pyvrs/reader.py
pyvrs/filter.py
