Metadata-Version: 2.1
Name: vrs
Version: 1.2.1
Summary: Python API for VRS
Home-page: https://github.com/facebookresearch/pyvrs
Author: Meta Reality Labs Research
License: Apache-2.0
Requires-Python: >=3.9
License-File: LICENSE
Requires-Dist: numpy
Requires-Dist: typing
Requires-Dist: dataclasses
